dbx_scd/__init__.py
dbx_scd/example.py
abx_scd-0.0.2.dist-info/LICENSE
abx_scd-0.0.2.dist-info/METADATA
abx_scd-0.0.2.dist-info/WHEEL
abx_scd-0.0.2.dist-info/top_level.txt
abx_scd-0.0.2.dist-info/RECORD
