Metadata-Version: 2.1
Name: abx-scd
Version: 0.0.2
Summary: Slowly Changing Dimensions implemenation with Databricks Delta Lake
Home-page: https://github.com/maye-msft/SlowlyChangingDimensionsInDeltaLake
Author: Sean Ma
Author-email: maye-msft@outlook.com
License: UNKNOWN
Project-URL: Bug Tracker, https://github.com/maye-msft/SlowlyChangingDimensionsInDeltaLake/issues
Platform: UNKNOWN
Classifier: Programming Language :: Python :: 3
Classifier: License :: OSI Approved :: MIT License
Classifier: Operating System :: OS Independent
Requires-Python: >=3.6
License-File: LICENSE
